ram_single_port/ram_single_port.vhd
--------------------------------------------------------
-- An n-bit address, m-bit word size, single-port RAM.
--------------------------------------------------------

LIBRARY ieee;
USE ieee.std_logic_1164.ALL;
USE ieee.numeric_std.ALL;

ENTITY single_port_ram IS
	GENERIC(	n: positive := 4;
				m: positive := 4);
	PORT(	rw, enable: IN std_logic;
			address: IN unsigned (n-1 DOWNTO 0);
			data: INOUT std_logic_vector (m-1 DOWNTO 0));
END ENTITY single_port_ram;

ARCHITECTURE behav OF single_port_ram IS
BEGIN 
	memory: PROCESS (rw, enable, address, data) IS
		TYPE rm IS ARRAY (0 TO 2**n-1) OF std_logic_vector (m-1 DOWNTO 0);
		VARIABLE word: rm;
	BEGIN
		data <= (OTHERS => 'Z');
		
		IF enable = '1' THEN
			IF rw = '1' THEN  						-- write location in memory
				word(to_integer(address)) := data;
			ELSE  									-- read location in memory
				data <= word(to_integer(address));
			END IF;
		END IF;
	END PROCESS memory;
END ARCHITECTURE behav;

ram_single_port/ram_single_port_test_bench.vhd
LIBRARY ieee;
USE ieee.std_logic_1164.ALL;
USE ieee.numeric_std.ALL;
use std.textio.all;


entity ram_single_port_test_bench is
end entity;


architecture test_bench of ram_single_port_test_bench is
  component single_port_ram is
    generic (n: positive:= 4;
             m: positive:= 4);
    port (rw, enable: in std_logic;
          address: in unsigned(n-1 downto 0);
          data: inout std_logic_vector (m-1 downto 0));
  end component;

  -- signals to RAM
  constant n: positive:=4;
  constant m: positive:=4;
  signal rw, enable: std_logic;
  signal address: unsigned(n-1 downto 0);
  signal data: std_logic_vector(m-1 downto 0);

begin
  -- applying inputs to ram
  dut: single_port_ram port map(rw, enable, address, data);


  -- applying testbench
  testing: process is

    -- files for vectors and results
    file vectors_file: text OPEN READ_MODE IS "test_vectors.txt";
    file results_file: text OPEN WRITE_MODE IS "results.txt";

    -- variables to parse the file
    variable simulation_l, result_l : line;
    variable message: string (1 TO 44);
    variable pause: time;

    variable rw_in_file, enable_in_file: bit;
    variable address_in_file:bit_vector(n-1 downto 0);
    variable data_in_file: bit_vector (m-1 downto 0);
    variable data_out_file: bit_vector (m-1 downto 0);

    begin
      --initial values
      rw <='1';
      enable <= '1';
      address <= "0000";
      data <= "0000";
      wait for 15 ns;

      -- first title line
      readline (vectors_file, simulation_l);
      -- test vectors file parsing
      while not endfile (vectors_file) loop

        -- reading simulation data from file
        readline (vectors_file, simulation_l);
        read (simulation_l, rw_in_file);
        read (simulation_l, enable_in_file);
        read (simulation_l, address_in_file);
        read (simulation_l, data_in_file);
        read (simulation_l, pause);
        read (simulation_l, data_out_file);
        read (simulation_l, message);

        -- Applying simulation inputs

        case rw_in_file is
          when '0'  => rw <= '0';
          when '1'  => rw <= '1';
          when others => null;
        end case;


        case enable_in_file is
          when '0'  => enable <= '0';
          when '1'  => enable <= '1';
          when others => null;
        end case;

        address <= unsigned(to_stdlogicvector(address_in_file));
        data <= to_stdlogicvector(data_in_file);

        wait for pause;


        -- writing output to results file
        write (result_l, string'("Time is now: "));
        write (result_l, NOW);

        write (result_l, string'(", rw="));
        write (result_l, rw_in_file);


        write (result_l, string'(", enable="));
        write (result_l, enable_in_file);


        write (result_l, string'(", address="));
        write (result_l, address_in_file);

        write (result_l, string'(", data_in="));
        write (result_l, data_in_file);

        write (result_l, string'(", out data="));
        -- write (result_l, data);

        write (result_l, string'(", Actual data="));
        write (result_l, data_out_file);


        -- checking for input validation
        if data /= to_stdlogicvector(data_out_file) then

          write (result_l, string'(" FAILED, Error Messages: "));
          write (result_l, message);

        else
          write (result_l, string'(" Test PASSED"));

        end if;

        -- writing into results file
        writeline (results_file, result_l);
      end loop;

      assert false report "End of Test";


    wait; -- kill loop
    end process testing;

end architecture;

ram_single_port/sim.vcd
$date
  Sun Jan 30 14:04:16 2022
$end
$version
  GHDL v0
$end
$timescale
  1 fs
$end
$scope module standard $end
$upscope $end
$scope module std_logic_1164 $end
$upscope $end
$scope module numeric_std $end
$upscope $end
$scope module textio $end
$upscope $end
$scope module ram_single_port_test_bench $end
$var reg 1 ! rw $end
$var reg 1 " enable $end
$var reg 4 # address[3:0] $end
$var reg 4 $ data[3:0] $end
$scope module dut $end
$var reg 1 % rw $end
$var reg 1 & enable $end
$var reg 4 ' address[3:0] $end
$var reg 4 ( data[3:0] $end
$upscope $end
$upscope $end
$enddefinitions $end
#0
1!
1"
b0000 #
b0000 $
1%
1&
b0000 '
b0000 (
#15000000
b1100 $
b1100 (
#30000000
#45000000
b1000 #
b0101 $
b1000 '
b0101 (
#60000000
#75000000
0!
b0000 #
b1100 $
0%
b0000 '
b1100 (
#90000000
0"
b1000 #
bZZZZ $
0&
b1000 '
bZZZZ (
#105000000
1!
1"
b1111 #
b1101 $
1%
1&
b1111 '
b1101 (
#120000000
#135000000
b1100 #
b1000 $
b1100 '
b1000 (
#150000000
#165000000
0!
b0000 #
b1100 $
0%
b0000 '
b1100 (
#180000000
1!
b1000 #
b1111 $
1%
b1000 '
b1111 (
#195000000
#210000000
0!
b1111 $
0%
b1111 (
