alu/alu.vhd
---------------------------------------------------------------------------
-- Entity and architecture declarations for an ALU using a CASE statement.
---------------------------------------------------------------------------

PACKAGE pack_a IS
   TYPE op_type IS (add, sub, mul, div);
END PACKAGE pack_a;

LIBRARY ieee;
USE ieee.numeric_bit.ALL;
USE WORK.pack_a.ALL;

ENTITY alu IS
   PORT( op: IN op_type;
         a, b : IN signed (3 DOWNTO 0);
         c : OUT signed (3 DOWNTO 0)); 
END ENTITY alu;

ARCHITECTURE alu OF alu IS
BEGIN 
   Palu: PROCESS (op, a, b) IS
   VARIABLE temp: signed (7 DOWNTO 0) := x"00";
   BEGIN 
     CASE op IS
       WHEN add => c <= a + b; 
       WHEN sub => c <= a - b; 
       WHEN mul => temp := a * b; c <= temp (3 DOWNTO 0);
       WHEN div => c <= a / b; 
     END CASE;
   END PROCESS Palu;
END ARCHITECTURE alu;

alu/alu_test_bench.vhd
LIBRARY ieee;
USE ieee.numeric_bit.ALL;
USE WORK.pack_a.ALL;
use std.textio.all;

entity alu_test_bench is
end entity alu_test_bench;


architecture test_bench of alu_test_bench is

  component alu is
    port(op: in op_type;
         a, b: in signed (3 downto 0);
         c: out signed (3 downto 0));
  end component;

  -- test signals
  signal op: op_type;
  signal a, b, c: signed (3 downto 0);

begin
  --applying inputs to the device under test
  dut: alu port map (op, a, b, c);

    -- Looping throw test cases
    testing: process is


    begin
      -- initial values
      op <= add;
      a <= "0000";
      b <= "0000";
      wait for 15 ns;

      op <= add;
      a <= "1111";
      b <= "1111";
      wait for 15 ns;



      op <= add;
      a <= "1100";
      b <= "0011";
      wait for 15 ns;


      op <= add;
      a <= "0111";
      b <= "0111";
      wait for 15 ns;


      op <= sub;
      a <= "0111";
      b <= "0111";
      wait for 15 ns;


      op <= sub;
      a <= "1100";
      b <= "0011";
      wait for 15 ns;



      op <= mul;
      a <= "0111";
      b <= "0001";
      wait for 15 ns;


      op <= mul;
      a <= "0111";
      b <= "0000";
      wait for 15 ns;


      op <= mul;
      a <= "1111";
      b <= "1100";
      wait for 15 ns;


      op <= mul;
      a <= "1101";
      b <= "0110";
      wait for 15 ns;


      op <= div;
      a <= "1101";
      b <= "0001";
      wait for 15 ns;


      op <= div;
      a <= "1101";
      b <= "0011";
      wait for 15 ns;


      op <= div;
      a <= "1101";
      b <= "0000";
      wait for 15 ns;

     wait; -- kill the process

    end process testing;

end architecture;

alu/sim.vcd
$date
  Tue Jan 25 01:15:45 2022
$end
$version
  GHDL v0
$end
$timescale
  1 fs
$end
$scope module standard $end
$upscope $end
$scope module numeric_bit $end
$upscope $end
$scope module pack_a $end
$upscope $end
$scope module textio $end
$upscope $end
$scope module alu_test_bench $end
$comment op is not handled $end
$var reg 4 ! a[3:0] $end
$var reg 4 " b[3:0] $end
$var reg 4 # c[3:0] $end
$scope module dut $end
$comment op is not handled $end
$var reg 4 $ a[3:0] $end
$var reg 4 % b[3:0] $end
$var reg 4 & c[3:0] $end
$upscope $end
$upscope $end
$enddefinitions $end
#0
b0000 !
b0000 "
b0000 #
b0000 $
b0000 %
b0000 &
#15000000
b1111 !
b1111 "
b1110 #
b1111 $
b1111 %
b1110 &
#30000000
b1100 !
b0011 "
b1111 #
b1100 $
b0011 %
b1111 &
#45000000
b0111 !
b0111 "
b1110 #
b0111 $
b0111 %
b1110 &
#60000000
b0000 #
b0000 &
#75000000
b1100 !
b0011 "
b1001 #
b1100 $
b0011 %
b1001 &
#90000000
b0111 !
b0001 "
b0111 #
b0111 $
b0001 %
b0111 &
#105000000
b0000 "
b0000 #
b0000 %
b0000 &
#120000000
b1111 !
b1100 "
b0100 #
b1111 $
b1100 %
b0100 &
#135000000
b1101 !
b0110 "
b1110 #
b1101 $
b0110 %
b1110 &
#150000000
b0001 "
b1101 #
b0001 %
b1101 &
#165000000
b0011 "
b1111 #
b0011 %
b1111 &
#180000000
b0000 "
b0001 #
b0000 %
b0001 &
