register_file/register_file.vhd
---------------------------------------------------------------------------
-- an n-bit address, m-bit word Register File with 2 reads and 2 writes
---------------------------------------------------------------------------


library ieee;
use ieee.std_logic_1164.all;
use ieee.numeric_std.all;


entity register_file is
  generic(n: positive:=5;
          m: positive:= 32);
  port(write_enable1, write_enable2, write_priority: in std_logic;
       read_reg1, read_reg2: in unsigned(n-1 downto 0);
       write_reg1, write_reg2: in unsigned(n-1 downto 0);
       write_data1, write_data2: in std_logic_vector(m-1 downto 0);
       read_data1, read_data2: out std_logic_vector(m-1 downto 0));
end entity register_file;


architecture rf of register_file is
begin

  rf_p: process(write_enable1, write_enable2, write_priority,
                read_reg1,read_reg2,
                write_reg1, write_reg2, write_data1, write_data2) is

    type DW is array (0 to 2**n -1) of std_logic_vector(m-1 downto 0);
    variable word: DW;
  begin

    -- corner case writing in same register
    if (write_enable1 = '1' and write_enable2 = '1') and
      (write_reg1 = write_reg2) then

      -- choose write_reg2
      if write_priority = '1' then
        word(to_integer(write_reg2)) := write_data2;

      -- choose write_reg1
      else
        word(to_integer(write_reg1)) := write_data1;
      end if;

    -- normal case different registers
    else

      -- write_reg1
      if write_enable1 = '1' then
        word(to_integer(write_reg1)) := write_data1;
      end if;


      -- write_reg2
      if write_enable2 = '1' then
        word(to_integer(write_reg2)) := write_data2;
      end if;

    end if; -- write

    -- reading registers (register file forwarding)
    read_data1 <= word(to_integer(read_reg1));
    read_data2 <= word(to_integer(read_reg2));


  end process rf_p;
end architecture rf;

register_file/register_file_test_bench.vhd
LIBRARY ieee;
USE ieee.std_logic_1164.ALL;
USE ieee.numeric_std.ALL;
use std.textio.all;


entity register_file_test_bench is
end entity;


architecture test_bench of register_file_test_bench is
  component register_file is
    generic(n: positive:= 4;
            m: positive:= 4);
    port(write_enable1, write_enable2, write_priority: in std_logic;
         read_reg1, read_reg2: in unsigned(n-1 downto 0);
         write_reg1, write_reg2: in unsigned(n-1 downto 0);
         write_data1, write_data2: in std_logic_vector(m-1 downto 0);
         read_data1, read_data2: out std_logic_vector(m-1 downto 0));
  end component;



  -- signals to RF
  constant n: positive:= 4;
  constant m: positive:= 4;

  signal write_enable1, write_enable2, write_priority: std_logic;
  signal read_reg1, read_reg2: unsigned(n-1 downto 0);
  signal write_reg1, write_reg2: unsigned(n-1 downto 0);
  signal write_data1, write_data2: std_logic_vector(m-1 downto 0);
  signal read_data1, read_data2: std_logic_vector(m-1 downto 0);

begin
  -- applying inputs to ram
  dut: register_file port map(write_enable1, write_enable2, write_priority, read_reg1, read_reg2, write_reg1, write_reg2, write_data1, write_data2, read_data1, read_data2);


  -- applying testbench
  testing: process is

    -- files for vectors and results
    file vectors_file: text OPEN READ_MODE IS "test_vectors.txt";
    file results_file: text OPEN WRITE_MODE IS "results.txt";

    -- variables to parse the file
    variable simulation_l, result_l, empty_l : line;
    variable message: string (1 TO 50);
    variable pause: time;


    variable write_enable1_in_file, write_enable2_in_file: bit;
    variable write_priority_in_file: bit;
    variable read_reg1_in_file: bit_vector(n-1 downto 0);
    variable read_reg2_in_file: bit_vector(n-1 downto 0);
    variable write_reg1_in_file: bit_vector(n-1 downto 0);
    variable write_reg2_in_file: bit_vector(n-1 downto 0);
    variable write_data1_in_file: bit_vector(m-1 downto 0);
    variable write_data2_in_file: bit_vector(m-1 downto 0);

    variable read_data1_out_file: bit_vector(m-1 downto 0);
    variable read_data2_out_file: bit_vector(m-1 downto 0);



    --function to map std_logic to bit
    function to_std_logic(b: bit) return std_logic is
      variable b_std_logic: std_logic;

    begin
      case b is
        when '0' => b_std_logic :='0';
        when '1' => b_std_logic :='1';
        when others => null;
      end case;

      return b_std_logic;

    end function;

    -- function to covert std to string
    function to_bstring(sl : std_logic) return string is
      variable sl_str_v : string(1 to 3);  -- std_logic image with quotes around
    begin
      sl_str_v := std_logic'image(sl);
      return "" & sl_str_v(2);  -- "" & character to get string
    end function;

    function to_bstring(slv : std_logic_vector) return string is
      alias    slv_norm : std_logic_vector(1 to slv'length) is slv;
      variable sl_str_v : string(1 to 1);  -- String of std_logic
      variable res_v    : string(1 to slv'length);
    begin
      for idx in slv_norm'range loop
        sl_str_v := to_bstring(slv_norm(idx));
        res_v(idx) := sl_str_v(1);
      end loop;
      return res_v;
    end function;

    begin
      --initial values
      write_enable1 <='1';
      write_enable2 <='1';
      write_priority <='0';

      read_reg1 <= (others => '0');
      read_reg2 <= (others => '0');

      write_reg1 <= (others => '0');
      write_reg2 <= (others => '0');
      write_data1 <= (others => '0');
      write_data2 <= (others => '0');
      wait for 15 ns;

      -- first title line
      readline (vectors_file, simulation_l);
      -- test vectors file parsing
      while not endfile (vectors_file) loop

        -- reading simulation data from file
        readline (vectors_file, simulation_l);
        read (simulation_l, write_enable1_in_file);
        read (simulation_l, write_enable2_in_file);
        read (simulation_l, write_priority_in_file);
        read (simulation_l, read_reg1_in_file);
        read (simulation_l, read_reg2_in_file);
        read (simulation_l, write_reg1_in_file);
        read (simulation_l, write_reg2_in_file);
        read (simulation_l, write_data1_in_file);
        read (simulation_l, write_data2_in_file);
        read (simulation_l, pause);
        read (simulation_l, read_data1_out_file);
        read (simulation_l, read_data2_out_file);
        read (simulation_l, message);

        -- Applying simulation inputs

        --initial values
        write_enable1 <= to_std_logic(write_enable1_in_file);
        write_enable2 <= to_std_logic(write_enable2_in_file);
        write_priority <= to_std_logic(write_priority_in_file);

        read_reg1 <= unsigned(to_stdlogicvector(read_reg1_in_file));
        read_reg2 <= unsigned(to_stdlogicvector(read_reg2_in_file));

        write_reg1 <= unsigned(to_stdlogicvector(write_reg1_in_file));
        write_reg2 <= unsigned(to_stdlogicvector(write_reg2_in_file));

        write_data1 <= to_stdlogicvector(write_data1_in_file);
        write_data2 <= to_stdlogicvector(write_data2_in_file);


        wait for pause;

        -- writing output to results file
        write (result_l, string'("Time is now: "));
        write (result_l, NOW);

        write (result_l, string'(", write_enable1="));
        write (result_l, write_enable1_in_file);

        write (result_l, string'(", write_enable2="));
        write (result_l, write_enable2_in_file);

        write (result_l, string'(", write_priority="));
        write (result_l, write_priority_in_file);

        write (result_l, string'(", read_reg1="));
        write (result_l, read_reg1_in_file);

        write (result_l, string'(", read_reg2="));
        write (result_l, read_reg2_in_file);

        write (result_l, string'(", write_reg1="));
        write (result_l, write_reg1_in_file);

        write (result_l, string'(", write_reg2="));
        write (result_l, write_reg2_in_file);

        write (result_l, string'(", write_data1="));
        write (result_l, write_data1_in_file);

        write (result_l, string'(", write_data2="));
        write (result_l, write_data2_in_file);

        write (result_l, string'(", actual read_data1="));
        write (result_l, read_data1_out_file);

        write (result_l, string'(", actual read_data2="));
        write (result_l, read_data2_out_file);

        write (result_l, string'(", read_data1="));
        write (result_l, to_bstring(read_data1));

        write (result_l, string'(", read_data2="));
        write (result_l, to_bstring(read_data2));


        -- checking for input validation
        if (read_data1 /= to_stdlogicvector(read_data1_out_file)) or
        (read_data2 /= to_stdlogicvector(read_data2_out_file))then

            write (result_l, string'(" FAILED, Error Messages: "));
            write (result_l, message);

          else
            write (result_l, string'(" Test PASSED"));

          end if;


        -- writing into results file
        writeline (results_file, result_l);
        writeline (results_file, empty_l);
      end loop;

      assert false report "End of Test";


    wait; -- kill loop
    end process testing;

end architecture;

register_file/sim.vcd
$date
  Sat Feb  5 00:15:16 2022
$end
$version
  GHDL v0
$end
$timescale
  1 fs
$end
$scope module standard $end
$upscope $end
$scope module std_logic_1164 $end
$upscope $end
$scope module numeric_std $end
$upscope $end
$scope module textio $end
$upscope $end
$scope module register_file_test_bench $end
$var reg 1 ! write_enable1 $end
$var reg 1 " write_enable2 $end
$var reg 1 # write_priority $end
$var reg 4 $ read_reg1[3:0] $end
$var reg 4 % read_reg2[3:0] $end
$var reg 4 & write_reg1[3:0] $end
$var reg 4 ' write_reg2[3:0] $end
$var reg 4 ( write_data1[3:0] $end
$var reg 4 ) write_data2[3:0] $end
$var reg 4 * read_data1[3:0] $end
$var reg 4 + read_data2[3:0] $end
$scope module dut $end
$var reg 1 , write_enable1 $end
$var reg 1 - write_enable2 $end
$var reg 1 . write_priority $end
$var reg 4 / read_reg1[3:0] $end
$var reg 4 0 read_reg2[3:0] $end
$var reg 4 1 write_reg1[3:0] $end
$var reg 4 2 write_reg2[3:0] $end
$var reg 4 3 write_data1[3:0] $end
$var reg 4 4 write_data2[3:0] $end
$var reg 4 5 read_data1[3:0] $end
$var reg 4 6 read_data2[3:0] $end
$upscope $end
$upscope $end
$enddefinitions $end
#0
1!
1"
0#
b0000 $
b0000 %
b0000 &
b0000 '
b0000 (
b0000 )
b0000 *
b0000 +
1,
1-
0.
b0000 /
b0000 0
b0000 1
b0000 2
b0000 3
b0000 4
b0000 5
b0000 6
#15000000
b0001 %
b0001 '
b0001 )
b0001 +
b0001 0
b0001 2
b0001 4
b0001 6
#30000000
0!
0"
0,
0-
#45000000
1!
1"
b1000 &
b1001 '
b1000 (
b1001 )
1,
1-
b1000 1
b1001 2
b1000 3
b1001 4
#60000000
0!
0"
b1000 $
b1001 %
b1000 *
b1001 +
0,
0-
b1000 /
b1001 0
b1000 5
b1001 6
#75000000
1!
1"
b1101 $
b1101 %
b1101 &
b1101 '
b1111 (
b0011 )
b1111 *
b1111 +
1,
1-
b1101 /
b1101 0
b1101 1
b1101 2
b1111 3
b0011 4
b1111 5
b1111 6
#90000000
1#
b0011 *
b0011 +
1.
b0011 5
b0011 6
#105000000
0"
b1001 $
b1001 %
b1001 &
b1001 '
b1001 (
b0111 )
b1001 *
b1001 +
0-
b1001 /
b1001 0
b1001 1
b1001 2
b1001 3
b0111 4
b1001 5
b1001 6
#120000000
0#
0.
#135000000
0!
1"
b0111 *
b0111 +
0,
1-
b0111 5
b0111 6
#150000000
1#
1.
#165000000
1!
b1101 $
b1100 &
b0011 '
b1010 (
b1011 )
b0011 *
1,
b1101 /
b1100 1
b0011 2
b1010 3
b1011 4
b0011 5
#180000000
0!
0"
b1100 $
b0011 %
b1010 *
b1011 +
0,
0-
b1100 /
b0011 0
b1010 5
b1011 6
